Metadata-Version: 2.1
Name: okttendas-package
Version: 0.0.0
Summary: A package including all Functions that Okttenda reuses.
Author: Okttenda
Author-email: 
Keywords: python
Classifier: Development Status :: 1 - Planning
Classifier: Intended Audience :: Developers
Classifier: Programming Language :: Python :: 3
Classifier: Operating System :: Unix
Classifier: Operating System :: MacOS :: MacOS X
Classifier: Operating System :: Microsoft :: Windows
License-File: LICENSE
